git_development_cli_tools/__init__.py
git_development_cli_tools/__main__.py
git_development_cli_tools/cli/__init__.py
git_development_cli_tools/cli/entrypoint.py
git_development_cli_tools/cli/main.py
git_development_cli_tools/package/__init__.py
git_development_cli_tools/package/bundle.py
git_development_cli_tools/package/settings.py
git_development_cli_tools/package/updates.py
git_development_cli_tools/package/version.py
git_development_cli_tools/prints/__init__.py
git_development_cli_tools/prints/boxes.py
git_development_cli_tools/prints/colors.py
git_development_cli_tools/system/__init__.py
git_development_cli_tools/system/platform.py
git_development_cli_tools/types/__init__.py
git_development_cli_tools/types/strings.py
git_development_cli_tools-0.1.0.dist-info/LICENSE
git_development_cli_tools-0.1.0.dist-info/METADATA
git_development_cli_tools-0.1.0.dist-info/WHEEL
git_development_cli_tools-0.1.0.dist-info/entry_points.txt
git_development_cli_tools-0.1.0.dist-info/top_level.txt
git_development_cli_tools-0.1.0.dist-info/RECORD
