Metadata-Version: 2.1
Name: git-development-cli-tools
Version: 0.1.0
Summary: Git development CLI tools for daily usage
Home-page: https://gitlab.com/RadianDevCore/tools/git-development-cli-tools
Author: Adrian DC
Author-email: radian.dc@gmail.com
License: Apache License 2.0
Project-URL: Bug Reports, https://gitlab.com/RadianDevCore/tools/git-development-cli-tools/-/issues
Project-URL: Changelog, https://gitlab.com/RadianDevCore/tools/git-development-cli-tools/blob/main/CHANGELOG.md
Project-URL: Documentation, https://gitlab.com/RadianDevCore/tools/git-development-cli-tools#git-development-cli-tools
Project-URL: Source, https://gitlab.com/RadianDevCore/tools/git-development-cli-tools
Project-URL: Statistics, https://pypistats.org/packages/git-development-cli-tools
Keywords: git git-development-cli-tools
Classifier: Environment :: Console
Classifier: Intended Audience :: Developers
Classifier: License :: OSI Approved :: Apache Software License
Classifier: Operating System :: OS Independent
Classifier: Programming Language :: Python :: 3
Classifier: Programming Language :: Python :: 3.8
Classifier: Programming Language :: Python :: 3.9
Classifier: Programming Language :: Python :: 3.10
Classifier: Programming Language :: Python :: 3.11
Classifier: Programming Language :: Python :: 3.12
Classifier: Topic :: Software Development
Classifier: Topic :: Utilities
Requires-Python: >=3,!=3.0.*,!=3.1.*,!=3.2.*,!=3.3.*,!=3.4.*,!=3.5.*,!=3.6.*,!=3.7.*
License-File: LICENSE
Requires-Dist: colored>=1.4.2
Requires-Dist: packaging>=24.0
Requires-Dist: setuptools>=45.1.0
Requires-Dist: update_checker>=0.18.0
